bantupay_sdk/__init__.py
bantupay_sdk-0.0.10.dist-info/LICENSE
bantupay_sdk-0.0.10.dist-info/METADATA
bantupay_sdk-0.0.10.dist-info/WHEEL
bantupay_sdk-0.0.10.dist-info/top_level.txt
bantupay_sdk-0.0.10.dist-info/RECORD
