Metadata-Version: 2.1
Name: bantupay-sdk
Version: 0.0.10
Summary: BantuPay SDK
Home-page: https://github.com/bantublockchain/bantupay-sdk-python
Author: Bantu Blockchain Foundation
Author-email: adevops@bantufoundation.org
License: UNKNOWN
Project-URL: Bug Tracker, https://github.com/bantublockchain/bantupay-sdk-python/issues
Platform: UNKNOWN
Classifier: Programming Language :: Python :: 3
Classifier: License :: OSI Approved :: MIT License
Classifier: Operating System :: OS Independent
Requires-Python: >=3.6
Requires-Dist: stellar-sdk (==3.1.1)
Requires-Dist: requests (==2.25.1)
